goth/__init__.py
goth/__main__.py
goth/address.py
goth/api_monitor/README.md
goth/api_monitor/__init__.py
goth/api_monitor/api-monitor.svg
goth/api_monitor/api_events.py
goth/api_monitor/nginx.conf
goth/assertions/README.md
goth/assertions/__init__.py
goth/assertions/assertions.py
goth/assertions/common.py
goth/assertions/monitor.py
goth/assertions/operators.py
goth/configuration.py
goth/default-assets/docker/README.md
goth/default-assets/docker/docker-compose.yml
goth/default-assets/docker/outbound-test.Dockerfile
goth/default-assets/docker/proxy-nginx.Dockerfile
goth/default-assets/docker/yagna-goth-deb.Dockerfile
goth/default-assets/docker/yagna-goth.Dockerfile
goth/default-assets/goth-config-testing.yml
goth/default-assets/goth-config.yml
goth/default-assets/keys/001.json
goth/default-assets/keys/002.json
goth/default-assets/keys/003.json
goth/default-assets/provider/cert-dir/cert-permissions.json
goth/default-assets/provider/cert-dir/foo_ca-chain.cert.pem
goth/default-assets/provider/cert-dir/partner-certificate.signed.json
goth/default-assets/provider/cert-dir/root-certificate.signed.json
goth/default-assets/provider/hardware.json
goth/default-assets/provider/presets.json
goth/default-assets/provider/rules.json
goth/default-assets/web-root/.gitignore
goth/default-assets/web-root/params.json
goth/default-assets/web-root/upload/.gitignore
goth/gftp.py
goth/interactive.py
goth/node.py
goth/payment_config.py
goth/project.py
goth/runner/__init__.py
goth/runner/cli/__init__.py
goth/runner/cli/base.py
goth/runner/cli/typing.py
goth/runner/cli/yagna_app_key_cmd.py
goth/runner/cli/yagna_id_cmd.py
goth/runner/cli/yagna_payment_cmd.py
goth/runner/container/__init__.py
goth/runner/container/build.py
goth/runner/container/compose.py
goth/runner/container/payment.py
goth/runner/container/utils.py
goth/runner/container/yagna.py
goth/runner/download/__init__.py
goth/runner/exceptions.py
goth/runner/log.py
goth/runner/log_monitor.py
goth/runner/probe/__init__.py
goth-0.22.1.dist-info/METADATA
goth-0.22.1.dist-info/WHEEL
goth-0.22.1.dist-info/licenses/LICENSE
goth-0.22.1.dist-info/RECORD
