Metadata-Version: 2.4
Name: goth
Version: 0.22.1
Summary: Golem Test Harness - integration testing framework
License: GPL-3.0
License-File: LICENSE
Author: Golem Factory
Author-email: contact@golem.network
Requires-Python: >=3.10.1,<4.0.0
Classifier: Development Status :: 4 - Beta
Classifier: Framework :: AsyncIO
Classifier: Framework :: Pytest
Classifier: Intended Audience :: Developers
Classifier: License :: OSI Approved :: GNU General Public License v3 (GPLv3)
Classifier: Natural Language :: English
Classifier: Programming Language :: Python :: 3
Classifier: Programming Language :: Python :: 3.11
Classifier: Programming Language :: Python :: 3.12
Classifier: Programming Language :: Python :: 3.13
Classifier: Programming Language :: Python :: 3.14
Classifier: Programming Language :: Python :: 3.8
Classifier: Topic :: Software Development :: Testing
Requires-Dist: aiohttp (>=3.12.14,<4.0.0)
Requires-Dist: ansicolors (>=1.1.8,<2.0.0)
Requires-Dist: docker (>=7.0,<8.0)
Requires-Dist: dpath (>=2.1,<3.0)
Requires-Dist: func_timeout (>=4.3,<5.0)
Requires-Dist: ghapi (>=1.0,<2.0)
Requires-Dist: markupsafe (>=2.1,<3.0)
Requires-Dist: pylproxy (==0.2.3)
Requires-Dist: pyyaml (>=6.0,<7.0)
Requires-Dist: transitions (>=0.9.0,<0.10.0)
Requires-Dist: typing_extensions (>=4.5,<5.0)
Requires-Dist: ya-tmp-pyapi (==0.7.0)
Project-URL: Repository, https://github.com/golemfactory/goth
